Metadata-Version: 2.1
Name: ia-uvg-redes-bayesianas
Version: 1.0
Summary: Redes Bayesianas - Universidad del Valle de Guatemala
Author-email: san20226@uvg.edu.gt
